super_repo/__init__.py
super_repo/example.json
super_repo/example_calculator.py
super_repo/example_google.py
super_repo-0.5.0.dist-info/LICENSE.txt
super_repo-0.5.0.dist-info/WHEEL
super_repo-0.5.0.dist-info/METADATA
super_repo-0.5.0.dist-info/RECORD
