Metadata-Version: 2.3
Name: super-repo
Version: 0.5.0
Summary: A template repo for research software.
Author-email: Ludwig Hülk <datenzentrum@rl-institut.de>
Requires-Python: >=3.10
Classifier: Development Status :: 4 - Beta
Classifier: License :: OSI Approved :: MIT License
Classifier: Natural Language :: English
Classifier: Operating System :: OS Independent
Classifier: Programming Language :: Python :: 3
Classifier: Programming Language :: Python :: 3.10
Requires-Dist: stringcase ~=1.2.0
Project-URL: Documentation, https://rl-institut.github.io/super-repo/latest/
Project-URL: Homepage, https://github.com/rl-institut/super-repo
Project-URL: Source, https://github.com/rl-institut/super-repo
